yacgol.py
yacgol-0.5.0.dist-info/METADATA
yacgol-0.5.0.dist-info/RECORD
yacgol-0.5.0.dist-info/WHEEL
yacgol-0.5.0.dist-info/entry_points.txt
yacgol-0.5.0.dist-info/top_level.txt
